QumuloUtils/__init__.py
QumuloUtils/qanalytics.py
QumuloUtils/qcluster.py
QumuloUtils/qlogger.py
QumuloUtils/timecall.py
QumuloUtils-1.3.0.dist-info/LICENSE.txt
QumuloUtils-1.3.0.dist-info/METADATA
QumuloUtils-1.3.0.dist-info/WHEEL
QumuloUtils-1.3.0.dist-info/top_level.txt
QumuloUtils-1.3.0.dist-info/RECORD
