Metadata-Version: 2.1
Name: QumuloUtils
Version: 1.3.0
Summary: Utility API routines to assist with the Qumulo clustered filesystem.
Home-page: http://www.qumulo.com/
Author: Michael Kade
Author-email: mkade@qumulo.com
License: LICENSE.txt
Keywords: Qumulo QF2 API Helpers
Platform: UNKNOWN
Requires-Dist: enum
Requires-Dist: arrow
Requires-Dist: logging
Requires-Dist: python-dateutil
Requires-Dist: qumulo-api
Requires-Dist: multiprocessing
